faststart
