Metadata-Version: 1.0
Name: cy-faststart
Version: 0.1.1
Summary: A faststart implementation written in Cython.
Home-page: https://github.com/jaredlunde/cy-faststart
Author: Jared Lunde
Author-email: jared@tessellate.io
License: MIT
Platform: UNKNOWN
